.clang-format
.gitignore
.pre-commit-config.yaml
.readthedocs.yml
MANIFEST.in
README.rst
environment.yaml
pyproject.toml
setup.cfg
setup.py
tox.ini
.github/workflows/ci_cron_weekly.yml
.github/workflows/ci_tests.yml
.github/workflows/release.yml
docs/Makefile
docs/conf.py
docs/index.rst
docs/make.bat
docs/pylira-logo.png
docs/pylira/changelog.rst
docs/pylira/developer.rst
docs/pylira/index.rst
docs/pylira/references.rst
docs/pylira/api/core.rst
docs/pylira/api/data.rst
docs/pylira/api/index.rst
docs/pylira/api/utils.rst
docs/pylira/user/data.rst
docs/pylira/user/index.rst
docs/pylira/user/tutorials/index.rst
docs/pylira/user/tutorials/notebooks/mcmc-deconvolution-intro.md
docs/pylira/user/tutorials/notebooks/point_source.md
licenses/LICENSE.rst
licenses/README.rst
licenses/TEMPLATE_LICENCE.rst
pylira/__init__.py
pylira/_astropy_init.py
pylira/conftest.py
pylira/core.py
pylira/version.py
pylira.egg-info/PKG-INFO
pylira.egg-info/SOURCES.txt
pylira.egg-info/dependency_links.txt
pylira.egg-info/not-zip-safe
pylira.egg-info/requires.txt
pylira.egg-info/top_level.txt
pylira/data/README.rst
pylira/data/__init__.py
pylira/data/core.py
pylira/data/files/chandra-counts-obs-id-4683.fits.gz
pylira/data/files/chandra-counts-obs-id-4684.fits.gz
pylira/data/files/chandra-psf-obs-id-4683.fits.gz
pylira/data/files/chandra-psf-obs-id-4684.fits.gz
pylira/data/files/lincoln.png
pylira/data/files/output-par.txt
pylira/data/files/output.txt
pylira/data/tests/__init__.py
pylira/data/tests/test_core.py
pylira/extern/__init__.py
pylira/src/lira.h
pylira/src/lirabind.cpp
pylira/tests/__init__.py
pylira/tests/test_core.py
pylira/utils/__init__.py
pylira/utils/convolution.py
pylira/utils/io.py
pylira/utils/plot.py
pylira/utils/priors.py
pylira/utils/tests/__init__.py
pylira/utils/tests/test_io.py
pylira/utils/tests/test_plot.py
pylira/utils/tests/test_priors.py