Metadata-Version: 2.1
Name: pylira
Version: 0.2
Summary: A Python package for Bayesian low-counts image reconstruction and analysis
Home-page: https://pylira.readthedocs.io/
Author: pylira developers
Author-email: 
License: GNU GPL v3+
Requires-Python: >=3.7
Provides-Extra: all
Provides-Extra: test
Provides-Extra: docs
License-File: licenses/LICENSE.rst
